porktrotterrice/__init__.py
porktrotterrice/wp.py
porktrotterrice-0.0.1.dist-info/METADATA
porktrotterrice-0.0.1.dist-info/WHEEL
porktrotterrice-0.0.1.dist-info/top_level.txt
porktrotterrice-0.0.1.dist-info/RECORD
