Metadata-Version: 2.1
Name: porktrotterrice
Version: 0.0.1
Summary: 好吃的猪脚饭
Author: wuchongchong
Author-email: 137928049@qq.com
License: MIT
Classifier: License :: OSI Approved :: MIT License
Classifier: Programming Language :: Python
Requires-Python: >=3.5
Requires-Dist: requests
